microprocessor/CBR.v
module CBR #(parameter SZ = 23)(
  input CLK,
  input [SZ-1:0] val_in,
  output [SZ-1:0] CS_bus
);
  reg [SZ-1:0] val = 'b0;

  always @(negedge CLK)
  begin
    val = val_in;
  end

  assign CS_bus = val;
endmodule

microprocessor/control_store.v
module control_store #(parameter SZ = 23, parameter N = 7, parameter pN = 128)(
  input [N-1:0] CAR,
  output [SZ-1:0] CBR
);
  parameter n = 4;

  parameter add = 0, comp = 1, sub = 2, xorr = 3, andd = 4, orr = 5, 
    pc_out = 6, increment = 7, WMFC = 8, rnw = 9, //wmfc = wait for memory function to complete, rnw = read not-write
    A_in = 10, B_in = 11, C_in = 12, D_in = 13, 
    A_out = 14, B_out = 15, C_out = 16, D_out = 17, MAR_in = 18, MBR_out = 19, IR_in = 20, select_decoder = 21, endd = SZ-1;

  parameter fetch = 0;

  reg [pN-1:0] ins_mem[SZ-1:0];

  integer i;

  initial
  begin
    for (i = 0; i < 100; i++)
      ins_mem[i] = 'b0;
  end

  //Fetch
  initial
  begin
    ins_mem[fetch * n][pc_out] = 1; ins_mem[fetch * n][increment] = 1; ins_mem[fetch * n][MAR_in] = 1;
    ins_mem[fetch * n + 1][rnw] = 1; ins_mem[fetch * n + 1][WMFC] = 1;
    ins_mem[fetch * n + 2][MBR_out] = 1; ins_mem[fetch * n + 2][IR_in] = 1; ins_mem[fetch * n + 2][select_decoder] = 1;
  end

  assign CBR = ins_mem[CAR];
endmodule

microprocessor/CAR.v
module CAR #(parameter N = 7)(
  input CLK,
  input [N-1:0] val_in,
  output [N-1:0] addr
);
  reg [N-1:0] val_out = 'b0;

  always @(posedge CLK)
  begin
    val_out <= val_in;
  end

  assign addr = val_out;

endmodule

microprocessor/NAG.v
module NAG #(parameter N = 7)(
  input [N-1:0] CAR,
  input [N-1:0] decoder,
  input reset,
  input select_decoder,
  input CLK,
  output [N-1:0] next_addr
);
  assign next_addr = (reset ? 'b0 : (select_decoder ? decoder : CAR + 1));

endmodule

microprocessor/decoder.v
module decoder #(parameter N = 7)(
  input [7:0] ins,
  output [N-1:0] addr
);
  assign addr = (ins[7:4] + 1) * 4;

endmodule

microprocessor/ram.v
module ram(
  input [7:0] MAR,
  input enable,
  input [7:0] bus,
  input rnw,
  output [7:0] MBR,
  output MFC
);
  reg [15:0] memo[7:0];
  reg [7:0] data_out = 'b0;
  initial
    memo[0] = 8'b1;
  reg tmp = 0;
  always @(posedge enable)
    begin
      if(rnw) data_out = memo[MAR[3:0]];
      else memo[MAR[3:0]] = bus;
      tmp = 1;
    end
  
  always @(negedge enable)
    tmp = 0;
  
  assign MFC = tmp;
  assign MBR = data_out;
  
endmodule

microprocessor/register_2.v
module register_2(
  input r_in,
  input r_out,
  input CLK,
  input [7:0] ibus,
  output [7:0] obus,
  output [7:0] value
);
  reg [7:0] val_in = 8'b0, val_out = 8'b0;
  
  always @(posedge CLK)
	begin
    if (r_in) val_in <= ibus;
    val_out <= val_in;
  end
  
  assign obus = (r_out ? val_out : 'bz);
  assign value = val_out;

endmodule

microprocessor/MBR.v
module MBR(
  input [7:0] val_in,
  input CLK,
  input MBR_out,
  output [7:0] obus
);
  reg [7:0] val_out;

  always @(posedge CLK)
  begin
    val_out <= val_in;
  end

  assign obus = (MBR_out) ? val_out : 'bz;
endmodule

microprocessor/cu.v
// add, comp, sub, xorr, andd, orr, pc_out, increment, WMFC, rnw, A_in, B_in , C_in , D_in, A_out, B_out , C_out , D_out, MAR_in, MBR_out, IR_in, endd
//
module cu #(parameter SZ = 23)(
  input CLK,
  input [7:0] ins,
  output [SZ-1:0] CS_bus
);
  wire [3:0] msb;
  wire [1:0] rd, rs;

  parameter add = 0, comp = 1, sub = 2, xorr = 3, andd = 4, orr = 5, 
    pc_out = 6, increment = 7, WMFC = 8, rnw = 9,
    A_in = 10, B_in = 11, C_in = 12, D_in = 13, 
    A_out = 14, B_out = 15, C_out = 16, D_out = 17, MAR_in = 18, MBR_out = 19, IR_in = 20, select_decoder = 21, endd = SZ-1;
  
  always @(posedge CLK)
    begin
      if (CS_bus[WMFC] == 0)
        begin
          if (CS_bus[endd])
            ;
        end
    end

  assign msb = ins[7:4];
  assign rd = ins[3:2];
  assign rs = ins[1:0];

endmodule

microprocessor/pc.v
module pc(
  input increment,
  input CLK,
  input pc_out,
  output [7:0] bus
);
  reg[7:0] addr_in = 8'b0, addr_out = 8'b0;
  always @(posedge CLK)
    begin
      if (increment) addr_in <= addr_out + 1;
      addr_out <= addr_in;
    end
  
  assign bus = (pc_out)? addr_out:'bz;
  
endmodule

microprocessor/start.v
module start(
  input clk
);
  parameter SZ = 23, N = 7, pN = 128;

  parameter add = 0, comp = 1, sub = 2, xorr = 3, andd = 4, orr = 5, 
    pc_out = 6, increment = 7, WMFC = 8, rnw = 9, //wmfc = wait for memory function to complete, rnw = read not-write
    A_in = 10, B_in = 11, C_in = 12, D_in = 13, 
    A_out = 14, B_out = 15, C_out = 16, D_out = 17, MAR_in = 18, MBR_out = 19, IR_in = 20, select_decoder = 21, endd = SZ-1;

  wire [7:0] bus;
  wire [SZ-1:0] CS_bus;
  wire [7:0] ins;

  wire MFC;
  wire [N-1:0] out_NAG, out_CAR, out_dec;
  wire [SZ-1:0] out_store;
  wire [7:0] out_A, out_IR, out_MAR, out_MBR, out_ram;
  
  pc program_counter(.increment(CS_bus[increment]), .CLK(clk), .pc_out(CS_bus[pc_out]), .bus(bus));
  cu control_unit(.CLK(clk), .ins(ins), .CS_bus(CS_bus));
  register_2 MAR(.r_in(CS_bus[MAR_in]), .r_out(1'b0), .CLK(clk), .ibus(bus), .obus(bus), .value(out_MAR));
  MBR mbr(.val_in(out_ram), .CLK(clk), .MBR_out(CS_bus[MBR_out]), .obus(bus));
  register_2 IR(.r_in(CS_bus[IR_in]), .r_out(1'b0), .CLK(clk), .ibus(bus), .obus(bus), .value(out_IR));
  ram RAM(.MAR(out_MAR), .enable(CS_bus[WMFC]), .bus(bus), .rnw(CS_bus[rnw]), .MBR(out_ram), .MFC(MFC));

  decoder dec(.ins(out_IR), .addr(out_dec));
  NAG nag(.CAR(out_CAR), .decoder(out_dec), .reset(CS_bus[endd]), .select_decoder(CS_bus[select_decoder]), .CLK(clk), .next_addr(out_NAG));
  CAR car(.CLK(clk), .val_in(out_NAG), .addr(out_CAR));
  control_store store(.CAR(out_CAR), .CBR(out_store));
  CBR cbr(.CLK(clk), .val_in(out_store), .CS_bus(CS_bus));

endmodule

microprocessor/testbench.v
module test_bench;
  reg clock;

  start boot(clock);
  
  initial
    begin
      $dumpfile("dump.vcd");
      $dumpvars;
    end
  
 initial #200 $finish;
 initial
   begin
    clock = 0;
    #5;
   	forever #5 clock = ~clock;
   end
endmodule

microprocessor/dump.vcd
$date
	Wed Nov 02 22:37:42 2022
$end
$version
	Icarus Verilog
$end
$timescale
	1s
$end
$scope module test_bench $end
$var reg 1 ! clock $end
$scope module boot $end
$var wire 8 " bus [7:0] $end
$var wire 1 ! clk $end
$var wire 8 # ins [7:0] $end
$var wire 22 $ out_store [21:0] $end
$var wire 8 % out_ram [7:0] $end
$var wire 7 & out_dec [6:0] $end
$var wire 7 ' out_NAG [6:0] $end
$var wire 8 ( out_MAR [7:0] $end
$var wire 8 ) out_IR [7:0] $end
$var wire 7 * out_CAR [6:0] $end
$var wire 1 + MFC $end
$var wire 22 , CS_bus [21:0] $end
$scope module IR $end
$var wire 1 ! CLK $end
$var wire 8 - ibus [7:0] $end
$var wire 8 . obus [7:0] $end
$var wire 1 / r_in $end
$var wire 1 0 r_out $end
$var wire 8 1 value [7:0] $end
$var reg 8 2 val_in [7:0] $end
$var reg 8 3 val_out [7:0] $end
$upscope $end
$scope module MAR $end
$var wire 1 ! CLK $end
$var wire 8 4 ibus [7:0] $end
$var wire 8 5 obus [7:0] $end
$var wire 1 6 r_in $end
$var wire 1 7 r_out $end
$var wire 8 8 value [7:0] $end
$var reg 8 9 val_in [7:0] $end
$var reg 8 : val_out [7:0] $end
$upscope $end
$scope module RAM $end
$var wire 8 ; MAR [7:0] $end
$var wire 8 < MBR [7:0] $end
$var wire 1 + MFC $end
$var wire 8 = bus [7:0] $end
$var wire 1 > enable $end
$var wire 1 ? rnw $end
$var reg 8 @ data_out [7:0] $end
$var reg 1 A tmp $end
$upscope $end
$scope module car $end
$var wire 1 ! CLK $end
$var wire 7 B val_in [6:0] $end
$var wire 7 C addr [6:0] $end
$var reg 7 D val_out [6:0] $end
$upscope $end
$scope module cbr $end
$var wire 1 ! CLK $end
$var wire 22 E val_in [21:0] $end
$var wire 22 F CS_bus [21:0] $end
$var reg 22 G val [21:0] $end
$upscope $end
$scope module control_unit $end
$var wire 1 ! CLK $end
$var wire 22 H CS_bus [21:0] $end
$var wire 8 I ins [7:0] $end
$var wire 2 J rs [1:0] $end
$var wire 2 K rd [1:0] $end
$var wire 4 L msb [3:0] $end
$upscope $end
$scope module dec $end
$var wire 8 M ins [7:0] $end
$var wire 7 N addr [6:0] $end
$upscope $end
$scope module mbr $end
$var wire 1 ! CLK $end
$var wire 1 O MBR_out $end
$var wire 8 P obus [7:0] $end
$var wire 8 Q val_in [7:0] $end
$var reg 8 R val_out [7:0] $end
$upscope $end
$scope module nag $end
$var wire 7 S CAR [6:0] $end
$var wire 1 ! CLK $end
$var wire 7 T decoder [6:0] $end
$var wire 1 U reset $end
$var wire 1 V select_decoder $end
$var wire 7 W next_addr [6:0] $end
$upscope $end
$scope module program_counter $end
$var wire 1 ! CLK $end
$var wire 8 X bus [7:0] $end
$var wire 1 Y increment $end
$var wire 1 Z pc_out $end
$var reg 8 [ addr_in [7:0] $end
$var reg 8 \ addr_out [7:0] $end
$upscope $end
$scope module store $end
$var wire 7 ] CAR [6:0] $end
$var wire 22 ^ CBR [21:0] $end
$var integer 32 _ i [31:0] $end
$upscope $end
$upscope $end
$upscope $end
$enddefinitions $end
#0
$dumpvars
b1100100 _
b1000000000011000000 ^
b0 ]
b0 \
b0 [
1Z
1Y
b0 X
b1 W
0V
0U
b100 T
b0 S
bx R
b0 Q
b0 P
0O
b100 N
b0 M
bz L
bz K
bz J
bz I
b1000000000011000000 H
b1000000000011000000 G
b1000000000011000000 F
b1000000000011000000 E
b0 D
b0 C
b1 B
0A
b0 @
0?
0>
b0 =
b0 <
b0 ;
b0 :
b0 9
b0 8
07
16
b0 5
b0 4
b0 3
b0 2
b0 1
00
0/
b0 .
b0 -
b1000000000011000000 ,
0+
b0 *
b0 )
b0 (
b1 '
b100 &
b0 %
b1000000000011000000 $
bz #
b0 "
0!
$end
#10
b10 '
b10 B
b10 W
b1100000000 $
b1100000000 E
b1100000000 ^
b1 [
b0 R
b1 *
b1 C
b1 D
b1 S
b1 ]
1!
#15
1+
1A
b1 %
b1 <
b1 Q
b1 @
bz "
bz -
bz .
bz 4
bz 5
bz =
bz P
bz X
1?
1>
06
0Z
0Y
b1100000000 ,
b1100000000 F
b1100000000 G
b1100000000 H
0!
#20
b11 '
b11 B
b11 W
b1110000000000000000000 $
b1110000000000000000000 E
b1110000000000000000000 ^
b10 *
b10 C
b10 D
b10 S
b10 ]
b1 R
b1 \
1!
#25
b0 '
b0 B
b0 W
0+
0A
b1 "
b1 -
b1 .
b1 4
b1 5
b1 =
b1 P
b1 X
1V
1U
0?
0>
1/
1O
b1110000000000000000000 ,
b1110000000000000000000 F
b1110000000000000000000 G
b1110000000000000000000 H
0!
#30
b1000000000011000000 $
b1000000000011000000 E
b1000000000011000000 ^
b1 2
b0 *
b0 C
b0 D
b0 S
b0 ]
1!
#35
b1 '
b1 B
b1 W
0V
0U
0/
0O
16
1Z
1Y
b1000000000011000000 ,
b1000000000011000000 F
b1000000000011000000 G
b1000000000011000000 H
0!
#40
b10 '
b10 B
b10 W
b1100000000 $
b1100000000 E
b1100000000 ^
b1 *
b1 C
b1 D
b1 S
b1 ]
b1 )
b1 1
b1 3
b1 M
b1 9
b10 [
1!
#45
1+
1A
bz "
bz -
bz .
bz 4
bz 5
bz =
bz P
bz X
1?
1>
06
0Z
0Y
b1100000000 ,
b1100000000 F
b1100000000 G
b1100000000 H
0!
#50
b11 '
b11 B
b11 W
b1110000000000000000000 $
b1110000000000000000000 E
b1110000000000000000000 ^
b10 \
b1 (
b1 8
b1 ;
b1 :
b10 *
b10 C
b10 D
b10 S
b10 ]
1!
#55
b0 '
b0 B
b0 W
0+
0A
b1 "
b1 -
b1 .
b1 4
b1 5
b1 =
b1 P
b1 X
1V
1U
0?
0>
1/
1O
b1110000000000000000000 ,
b1110000000000000000000 F
b1110000000000000000000 G
b1110000000000000000000 H
0!
#60
b1000000000011000000 $
b1000000000011000000 E
b1000000000011000000 ^
b0 *
b0 C
b0 D
b0 S
b0 ]
1!
#65
b1 '
b1 B
b1 W
b10 "
b10 -
b10 .
b10 4
b10 5
b10 =
b10 P
b10 X
0V
0U
0/
0O
16
1Z
1Y
b1000000000011000000 ,
b1000000000011000000 F
b1000000000011000000 G
b1000000000011000000 H
0!
#70
b10 '
b10 B
b10 W
b1100000000 $
b1100000000 E
b1100000000 ^
b11 [
b10 9
b1 *
b1 C
b1 D
b1 S
b1 ]
1!
#75
1+
1A
bx %
bx <
bx Q
bx @
bz "
bz -
bz .
bz 4
bz 5
bz =
bz P
bz X
1?
1>
06
0Z
0Y
b1100000000 ,
b1100000000 F
b1100000000 G
b1100000000 H
0!
#80
b11 '
b11 B
b11 W
b1110000000000000000000 $
b1110000000000000000000 E
b1110000000000000000000 ^
b10 *
b10 C
b10 D
b10 S
b10 ]
bx R
b10 (
b10 8
b10 ;
b10 :
b11 \
1!
#85
b0 '
b0 B
b0 W
0+
0A
bx "
bx -
bx .
bx 4
bx 5
bx =
bx P
bx X
1V
1U
0?
0>
1/
1O
b1110000000000000000000 ,
b1110000000000000000000 F
b1110000000000000000000 G
b1110000000000000000000 H
0!
#90
b1000000000011000000 $
b1000000000011000000 E
b1000000000011000000 ^
bx 2
b0 *
b0 C
b0 D
b0 S
b0 ]
1!
#95
b1 '
b1 B
b1 W
b11 "
b11 -
b11 .
b11 4
b11 5
b11 =
b11 P
b11 X
0V
0U
0/
0O
16
1Z
1Y
b1000000000011000000 ,
b1000000000011000000 F
b1000000000011000000 G
b1000000000011000000 H
0!
#100
b10 '
b10 B
b10 W
b1100000000 $
b1100000000 E
b1100000000 ^
bx &
bx N
bx T
b1 *
b1 C
b1 D
b1 S
b1 ]
bx )
bx 1
bx 3
bx M
b11 9
b100 [
1!
#105
1+
1A
bz "
bz -
bz .
bz 4
bz 5
bz =
bz P
bz X
1?
1>
06
0Z
0Y
b1100000000 ,
b1100000000 F
b1100000000 G
b1100000000 H
0!
#110
b11 '
b11 B
b11 W
b1110000000000000000000 $
b1110000000000000000000 E
b1110000000000000000000 ^
b100 \
b11 (
b11 8
b11 ;
b11 :
b10 *
b10 C
b10 D
b10 S
b10 ]
1!
#115
b0 '
b0 B
b0 W
0+
0A
bx "
bx -
bx .
bx 4
bx 5
bx =
bx P
bx X
1V
1U
0?
0>
1/
1O
b1110000000000000000000 ,
b1110000000000000000000 F
b1110000000000000000000 G
b1110000000000000000000 H
0!
#120
b1000000000011000000 $
b1000000000011000000 E
b1000000000011000000 ^
b0 *
b0 C
b0 D
b0 S
b0 ]
1!
#125
b1 '
b1 B
b1 W
b100 "
b100 -
b100 .
b100 4
b100 5
b100 =
b100 P
b100 X
0V
0U
0/
0O
16
1Z
1Y
b1000000000011000000 ,
b1000000000011000000 F
b1000000000011000000 G
b1000000000011000000 H
0!
#130
b10 '
b10 B
b10 W
b1100000000 $
b1100000000 E
b1100000000 ^
b101 [
b100 9
b1 *
b1 C
b1 D
b1 S
b1 ]
1!
#135
1+
1A
bz "
bz -
bz .
bz 4
bz 5
bz =
bz P
bz X
1?
1>
06
0Z
0Y
b1100000000 ,
b1100000000 F
b1100000000 G
b1100000000 H
0!
#140
b11 '
b11 B
b11 W
b1110000000000000000000 $
b1110000000000000000000 E
b1110000000000000000000 ^
b10 *
b10 C
b10 D
b10 S
b10 ]
b100 (
b100 8
b100 ;
b100 :
b101 \
1!
#145
b0 '
b0 B
b0 W
0+
0A
bx "
bx -
bx .
bx 4
bx 5
bx =
bx P
bx X
1V
1U
0?
0>
1/
1O
b1110000000000000000000 ,
b1110000000000000000000 F
b1110000000000000000000 G
b1110000000000000000000 H
0!
#150
b1000000000011000000 $
b1000000000011000000 E
b1000000000011000000 ^
b0 *
b0 C
b0 D
b0 S
b0 ]
1!
#155
b1 '
b1 B
b1 W
b101 "
b101 -
b101 .
b101 4
b101 5
b101 =
b101 P
b101 X
0V
0U
0/
0O
16
1Z
1Y
b1000000000011000000 ,
b1000000000011000000 F
b1000000000011000000 G
b1000000000011000000 H
0!
#160
b10 '
b10 B
b10 W
b1100000000 $
b1100000000 E
b1100000000 ^
b1 *
b1 C
b1 D
b1 S
b1 ]
b101 9
b110 [
1!
#165
1+
1A
bz "
bz -
bz .
bz 4
bz 5
bz =
bz P
bz X
1?
1>
06
0Z
0Y
b1100000000 ,
b1100000000 F
b1100000000 G
b1100000000 H
0!
#170
b11 '
b11 B
b11 W
b1110000000000000000000 $
b1110000000000000000000 E
b1110000000000000000000 ^
b110 \
b101 (
b101 8
b101 ;
b101 :
b10 *
b10 C
b10 D
b10 S
b10 ]
1!
#175
b0 '
b0 B
b0 W
0+
0A
bx "
bx -
bx .
bx 4
bx 5
bx =
bx P
bx X
1V
1U
0?
0>
1/
1O
b1110000000000000000000 ,
b1110000000000000000000 F
b1110000000000000000000 G
b1110000000000000000000 H
0!
#180
b1000000000011000000 $
b1000000000011000000 E
b1000000000011000000 ^
b0 *
b0 C
b0 D
b0 S
b0 ]
1!
#185
b1 '
b1 B
b1 W
b110 "
b110 -
b110 .
b110 4
b110 5
b110 =
b110 P
b110 X
0V
0U
0/
0O
16
1Z
1Y
b1000000000011000000 ,
b1000000000011000000 F
b1000000000011000000 G
b1000000000011000000 H
0!
#190
b10 '
b10 B
b10 W
b1100000000 $
b1100000000 E
b1100000000 ^
b111 [
b110 9
b1 *
b1 C
b1 D
b1 S
b1 ]
1!
#195
1+
1A
bz "
bz -
bz .
bz 4
bz 5
bz =
bz P
bz X
1?
1>
06
0Z
0Y
b1100000000 ,
b1100000000 F
b1100000000 G
b1100000000 H
0!
#200
b11 '
b11 B
b11 W
b1110000000000000000000 $
b1110000000000000000000 E
b1110000000000000000000 ^
b10 *
b10 C
b10 D
b10 S
b10 ]
b110 (
b110 8
b110 ;
b110 :
b111 \
1!
