microprocessor/register_2.v
module register_2(
  input r_in,
  input r_out,
  input CLK,
  input [7:0] ibus,
  output [7:0] obus,
  output [7:0] value
);
  reg [7:0] val_out = 8'b0;
  
  always @(posedge CLK)
	begin
    if (r_in) val_out = ibus;
  end
  
  assign obus = (r_out ? val_out : 'bz);
  assign value = val_out;

endmodule

microprocessor/CBR.v
module CBR #(parameter SZ = 24)(
  input CLK,
  input [SZ-1:0] val_in,
  output [SZ-1:0] val_out
);
  reg [SZ-1:0] val = 'b0;

  always @(negedge CLK)
  begin
    val = val_in;
  end

  assign CS_bus = val;
endmodule

microprocessor/control_store.v
module control_store #(parameter SZ = 24, parameter N = 7, parameter pN = 128)(
  input [N-1:0] CAR,
  output [SZ-1:0] CBR
);
  parameter n = 4;

  parameter add = 0, comp = 1, sub = 2, xorr = 3, andd = 4, orr = 5, 
    pc_out = 6, increment = 7, WMFC = 8, rnw = 9, //wmfc = wait for memory function to complete, rnw = read not-write
    A_in = 10, B_in = 11, C_in = 12, D_in = 13, 
    A_out = 14, B_out = 15, C_out = 16, D_out = 17, MAR_in = 18, MBR_out = 19, IR_in = 20, IR_out = 21, select_decoder = 22, endd = SZ-1;

  parameter fetch = 0, load = 1, store = 2, move_immediate = 3, move_register = 4;

  reg [pN-1:0] ins_mem[SZ-1:0];

  integer i;

  initial
  begin
    for (i = 0; i < 100; i++)
      ins_mem[i] = 'b0;
  end

  //Fetch
  initial
  begin
    ins_mem[fetch * n][pc_out] = 1; ins_mem[fetch * n][increment] = 1; ins_mem[fetch * n][MAR_in] = 1;
    ins_mem[fetch * n + 1][rnw] = 1; ins_mem[fetch * n + 1][WMFC] = 1;
    ins_mem[fetch * n + 2][MBR_out] = 1; ins_mem[fetch * n + 2][IR_in] = 1;
    ins_mem[fetch * n + 3][select_decoder] = 1;
  end

  //Load LD
  initial
  begin
    ins_mem[load * n][IR_out] = 1; ins_mem[load * n][MAR_in] = 1;
    ins_mem[load * n + 1][rnw] = 1; ins_mem[load * n + 1][WMFC] = 1;
    ins_mem[load * n + 2][MBR_out] = 1; ins_mem[load * n + 2][A_in] = 1; ins_mem[load * n + 2][endd] = 1;
  end
  
  //Store ST
  initial
  begin
    ins_mem[store * n][IR_out] = 1; ins_mem[store * n][MAR_in] = 1;
    ins_mem[store * n + 1][rnw] = 0; ins_mem[store * n + 1][WMFC] = 1; ins_mem[store * n + 2][A_out] = 1; ins_mem[store * n + 2][endd] = 1;
  end

  //Move_immediate MI

  //Move_register
  ins_mem[move_register * n]

  assign CBR = ins_mem[CAR];
endmodule

microprocessor/CAR.v
module CAR #(parameter N = 7)(
  input CLK,
  input [N-1:0] val_in,
  output [N-1:0] addr
);
  reg [N-1:0] val_out = 'b0;

  always @(posedge CLK)
  begin
    val_out <= val_in;
  end

  assign addr = val_out;

endmodule

microprocessor/NAG.v
module NAG #(parameter N = 7)(
  input [N-1:0] CAR,
  input [N-1:0] decoder,
  input reset,
  input select_decoder,
  input CLK,
  output [N-1:0] next_addr
);
  assign next_addr = (reset ? 'b0 : (select_decoder ? decoder : CAR + 1));

endmodule

microprocessor/decoder.v
module decoder #(parameter N = 7)(
  input [7:0] ins,
  output [N-1:0] addr
  output 
);
  assign addr = (ins[7:4] + 1) * 4;

endmodule

microprocessor/ram.v
module ram(
  input CLK,
  input [7:0] MAR,
  input enable,
  input [7:0] bus,
  input rnw,
  output [7:0] MBR,
  output MFC
);
  reg [7:0] memo[15:0];
  reg [7:0] data_out = 'b0;
  initial
  begin
    memo[0] = 8'b00001001;
    memo[1] = 8'b00001000;
    memo[2] = 8'b00010101;
    memo[3] = 8'b00001010;
    memo[4] = 8'b00000101;
    memo[8] = 8'b01010101;
    memo[9] = 8'b00000011;
    memo[10] = 8'd5;
  end

  reg tmp = 0;
  always @(posedge enable)
    begin
      if(rnw) data_out = memo[MAR[3:0]];
      tmp = 1;
    end

  always @(posedge CLK)
    begin
      if (enable & !rnw) memo[MAR[3:0]] = bus;
      if (enable) tmp = 1;
    end
  
  always @(negedge enable)
    tmp = 0;
  
  assign MFC = tmp;
  assign MBR = data_out;
  
endmodule

microprocessor/cu.v
// add, comp, sub, xorr, andd, orr, pc_out, increment, WMFC, rnw, A_in, B_in , C_in , D_in, A_out, B_out , C_out , D_out, MAR_in, MBR_out, IR_in, endd
//
module cu #(parameter SZ = 24)(
  input CLK,
  input [7:0] ins,
  output [SZ-1:0] CS_bus
);
  wire [3:0] msb;
  wire [1:0] rd, rs;

  parameter add = 0, comp = 1, sub = 2, xorr = 3, andd = 4, orr = 5, 
    pc_out = 6, increment = 7, WMFC = 8, rnw = 9,
    A_in = 10, B_in = 11, C_in = 12, D_in = 13, 
    A_out = 14, B_out = 15, C_out = 16, D_out = 17, MAR_in = 18, MBR_out = 19, IR_in = 20, IR_out = 21, select_decoder = 22, endd = SZ-1;
  
  always @(posedge CLK)
    begin
      if (CS_bus[WMFC] == 0)
        begin
          if (CS_bus[endd])
            ;
        end
    end

  assign msb = ins[7:4];
  assign rd = ins[3:2];
  assign rs = ins[1:0];

endmodule

microprocessor/pc.v
module pc(
  input increment,
  input CLK,
  input pc_out,
  output [7:0] bus
);
  reg[7:0] addr_in = 8'b1000, addr_out = 8'b1000;
  always @(posedge CLK)
    begin
      if (increment) addr_in <= addr_out + 1;
      addr_out <= addr_in;
    end
  
  assign bus = (pc_out)? addr_out:'bz;
  
endmodule

microprocessor/start.v
module start(
  input clk
);
  parameter SZ = 24, N = 7, pN = 128;

  parameter add = 0, comp = 1, sub = 2, xorr = 3, andd = 4, orr = 5, 
    pc_out = 6, increment = 7, WMFC = 8, rnw = 9, //wmfc = wait for memory function to complete, rnw = read not-write
    A_in = 10, B_in = 11, C_in = 12, D_in = 13, 
    A_out = 14, B_out = 15, C_out = 16, D_out = 17, MAR_in = 18, MBR_out = 19, IR_in = 20, IR_out = 21, select_decoder = 22, endd = SZ-1;

  wire [7:0] bus;
  wire [SZ-1:0] CS_bus;
  wire [7:0] ins;

  wire MFC;
  wire [N-1:0] out_NAG, out_CAR, out_dec;
  wire [SZ-1:0] out_store;
  wire [7:0] out_A, out_IR, out_MAR, out_MBR, out_ram;
  
  pc program_counter(.increment(CS_bus[increment]), .CLK(clk), .pc_out(CS_bus[pc_out]), .bus(bus));
  cu control_unit(.CLK(clk), .ins(ins), .CS_bus(CS_bus));
  register_2 MAR(.r_in(CS_bus[MAR_in]), .r_out(1'b0), .CLK(clk), .ibus(bus), .obus(bus), .value(out_MAR));
  register_2 MBR(.r_in(1'b1), .r_out(CS_bus[MBR_out]), .CLK(clk), .ibus(out_ram), .obus(bus), .value(out_MBR));
  register_2 IR(.r_in(CS_bus[IR_in]), .r_out(CS_bus[IR_out]), .CLK(clk), .ibus(bus), .obus(bus), .value(out_IR));
  ram RAM(.CLK(clk), .MAR(out_MAR), .enable(CS_bus[WMFC]), .bus(bus), .rnw(CS_bus[rnw]), .MBR(out_ram), .MFC(MFC));

  decoder dec(.ins(out_IR), .addr(out_dec));
  NAG nag(.CAR(out_CAR), .decoder(out_dec), .reset(CS_bus[endd]), .select_decoder(CS_bus[select_decoder]), .CLK(clk), .next_addr(out_NAG));
  CAR car(.CLK(clk), .val_in(out_NAG), .addr(out_CAR));
  control_store store(.CAR(out_CAR), .CBR(out_store));
  CBR cbr(.CLK(clk), .val_in(out_store), .CS_bus(CS_bus));

  register_2 A(.r_in(CS_bus[A_in]), .r_out(CS_bus[A_out]), .CLK(clk), .ibus(bus), .obus(bus), .value(out_A));

endmodule

microprocessor/testbench.v
module test_bench;
  reg clock;

  start boot(clock);
  
  initial
    begin
      $dumpfile("dump.vcd");
      $dumpvars;
    end
  
 initial #400 $finish;
 initial
   begin
    clock = 0;
    #5;
   	forever #5 clock = ~clock;
   end
endmodule

microprocessor/dump.vcd
$date
	Thu Nov 03 20:28:42 2022
$end
$version
	Icarus Verilog
$end
$timescale
	1s
$end
$scope module test_bench $end
$var reg 1 ! clock $end
$scope module boot $end
$var wire 8 " bus [7:0] $end
$var wire 1 ! clk $end
$var wire 8 # ins [7:0] $end
$var wire 24 $ out_store [23:0] $end
$var wire 8 % out_ram [7:0] $end
$var wire 7 & out_dec [6:0] $end
$var wire 7 ' out_NAG [6:0] $end
$var wire 8 ( out_MBR [7:0] $end
$var wire 8 ) out_MAR [7:0] $end
$var wire 8 * out_IR [7:0] $end
$var wire 7 + out_CAR [6:0] $end
$var wire 8 , out_A [7:0] $end
$var wire 1 - MFC $end
$var wire 24 . CS_bus [23:0] $end
$scope module A $end
$var wire 1 ! CLK $end
$var wire 8 / ibus [7:0] $end
$var wire 8 0 obus [7:0] $end
$var wire 1 1 r_in $end
$var wire 1 2 r_out $end
$var wire 8 3 value [7:0] $end
$var reg 8 4 val_out [7:0] $end
$upscope $end
$scope module IR $end
$var wire 1 ! CLK $end
$var wire 8 5 ibus [7:0] $end
$var wire 8 6 obus [7:0] $end
$var wire 1 7 r_in $end
$var wire 1 8 r_out $end
$var wire 8 9 value [7:0] $end
$var reg 8 : val_out [7:0] $end
$upscope $end
$scope module MAR $end
$var wire 1 ! CLK $end
$var wire 8 ; ibus [7:0] $end
$var wire 8 < obus [7:0] $end
$var wire 1 = r_in $end
$var wire 1 > r_out $end
$var wire 8 ? value [7:0] $end
$var reg 8 @ val_out [7:0] $end
$upscope $end
$scope module MBR $end
$var wire 1 ! CLK $end
$var wire 8 A obus [7:0] $end
$var wire 1 B r_in $end
$var wire 1 C r_out $end
$var wire 8 D value [7:0] $end
$var wire 8 E ibus [7:0] $end
$var reg 8 F val_out [7:0] $end
$upscope $end
$scope module RAM $end
$var wire 1 ! CLK $end
$var wire 8 G MAR [7:0] $end
$var wire 8 H MBR [7:0] $end
$var wire 1 - MFC $end
$var wire 8 I bus [7:0] $end
$var wire 1 J enable $end
$var wire 1 K rnw $end
$var reg 8 L data_out [7:0] $end
$var reg 1 M tmp $end
$upscope $end
$scope module car $end
$var wire 1 ! CLK $end
$var wire 7 N val_in [6:0] $end
$var wire 7 O addr [6:0] $end
$var reg 7 P val_out [6:0] $end
$upscope $end
$scope module cbr $end
$var wire 1 ! CLK $end
$var wire 24 Q val_in [23:0] $end
$var wire 24 R CS_bus [23:0] $end
$var reg 24 S val [23:0] $end
$upscope $end
$scope module control_unit $end
$var wire 1 ! CLK $end
$var wire 24 T CS_bus [23:0] $end
$var wire 8 U ins [7:0] $end
$var wire 2 V rs [1:0] $end
$var wire 2 W rd [1:0] $end
$var wire 4 X msb [3:0] $end
$upscope $end
$scope module dec $end
$var wire 8 Y ins [7:0] $end
$var wire 7 Z addr [6:0] $end
$upscope $end
$scope module nag $end
$var wire 7 [ CAR [6:0] $end
$var wire 1 ! CLK $end
$var wire 7 \ decoder [6:0] $end
$var wire 1 ] reset $end
$var wire 1 ^ select_decoder $end
$var wire 7 _ next_addr [6:0] $end
$upscope $end
$scope module program_counter $end
$var wire 1 ! CLK $end
$var wire 8 ` bus [7:0] $end
$var wire 1 a increment $end
$var wire 1 b pc_out $end
$var reg 8 c addr_in [7:0] $end
$var reg 8 d addr_out [7:0] $end
$upscope $end
$scope module store $end
$var wire 7 e CAR [6:0] $end
$var wire 24 f CBR [23:0] $end
$var integer 32 g i [31:0] $end
$upscope $end
$upscope $end
$upscope $end
$enddefinitions $end
#0
$dumpvars
b1100100 g
b1000000000011000000 f
b0 e
b0 d
b0 c
1b
1a
b0 `
b1 _
0^
0]
b100 \
b0 [
b100 Z
b0 Y
bz X
bz W
bz V
bz U
b1000000000011000000 T
b1000000000011000000 S
b1000000000011000000 R
b1000000000011000000 Q
b0 P
b0 O
b1 N
0M
b0 L
0K
0J
b0 I
b0 H
b0 G
b0 F
b0 E
b0 D
0C
1B
b0 A
b0 @
b0 ?
0>
1=
b0 <
b0 ;
b0 :
b0 9
08
07
b0 6
b0 5
b0 4
b0 3
02
01
b0 0
b0 /
b1000000000011000000 .
0-
b0 ,
b0 +
b0 *
b0 )
b0 (
b1 '
b100 &
b0 %
b1000000000011000000 $
bz #
b0 "
0!
$end
#10
b10 '
b10 N
b10 _
b1100000000 $
b1100000000 Q
b1100000000 f
b1 c
b1 +
b1 O
b1 P
b1 [
b1 e
1!
#15
1-
1M
b1001 %
b1001 E
b1001 H
b1001 L
bz "
bz /
bz 0
bz 5
bz 6
bz ;
bz <
bz A
bz I
bz `
1K
1J
0=
0b
0a
b1100000000 .
b1100000000 R
b1100000000 S
b1100000000 T
0!
#20
b11 '
b11 N
b11 _
b110000000000000000000 $
b110000000000000000000 Q
b110000000000000000000 f
b10 +
b10 O
b10 P
b10 [
b10 e
b1 d
b1001 (
b1001 D
b1001 F
1!
#25
0-
0M
b1001 "
b1001 /
b1001 0
b1001 5
b1001 6
b1001 ;
b1001 <
b1001 A
b1001 I
b1001 `
0K
0J
17
1C
b110000000000000000000 .
b110000000000000000000 R
b110000000000000000000 S
b110000000000000000000 T
0!
#30
b100 '
b100 N
b100 _
b10000000000000000000000 $
b10000000000000000000000 Q
b10000000000000000000000 f
b11 +
b11 O
b11 P
b11 [
b11 e
b1001 *
b1001 9
b1001 Y
b1001 :
1!
#35
bz "
bz /
bz 0
bz 5
bz 6
bz ;
bz <
bz A
bz I
bz `
1^
07
0C
b10000000000000000000000 .
b10000000000000000000000 R
b10000000000000000000000 S
b10000000000000000000000 T
0!
#40
b1001000000000000000000 $
b1001000000000000000000 Q
b1001000000000000000000 f
b100 +
b100 O
b100 P
b100 [
b100 e
1!
#45
b101 '
b101 N
b101 _
b1001 "
b1001 /
b1001 0
b1001 5
b1001 6
b1001 ;
b1001 <
b1001 A
b1001 I
b1001 `
0^
18
1=
b1001000000000000000000 .
b1001000000000000000000 R
b1001000000000000000000 S
b1001000000000000000000 T
0!
#50
b110 '
b110 N
b110 _
b1100000000 $
b1100000000 Q
b1100000000 f
b101 +
b101 O
b101 P
b101 [
b101 e
b1001 )
b1001 ?
b1001 G
b1001 @
1!
#55
1-
1M
b11 %
b11 E
b11 H
b11 L
bz "
bz /
bz 0
bz 5
bz 6
bz ;
bz <
bz A
bz I
bz `
1K
1J
08
0=
b1100000000 .
b1100000000 R
b1100000000 S
b1100000000 T
0!
#60
b111 '
b111 N
b111 _
b100010000000010000000000 $
b100010000000010000000000 Q
b100010000000010000000000 f
b110 +
b110 O
b110 P
b110 [
b110 e
b11 (
b11 D
b11 F
1!
#65
b0 '
b0 N
b0 _
0-
0M
b11 "
b11 /
b11 0
b11 5
b11 6
b11 ;
b11 <
b11 A
b11 I
b11 `
11
1]
0K
0J
1C
b100010000000010000000000 .
b100010000000010000000000 R
b100010000000010000000000 S
b100010000000010000000000 T
0!
#70
b1000000000011000000 $
b1000000000011000000 Q
b1000000000011000000 f
b0 +
b0 O
b0 P
b0 [
b0 e
b11 ,
b11 3
b11 4
1!
#75
b1 '
b1 N
b1 _
b1 "
b1 /
b1 0
b1 5
b1 6
b1 ;
b1 <
b1 A
b1 I
b1 `
01
0]
0C
1=
1b
1a
b1000000000011000000 .
b1000000000011000000 R
b1000000000011000000 S
b1000000000011000000 T
0!
#80
b10 '
b10 N
b10 _
b1100000000 $
b1100000000 Q
b1100000000 f
b1 +
b1 O
b1 P
b1 [
b1 e
b10 c
b1 )
b1 ?
b1 G
b1 @
1!
#85
1-
1M
b1000 %
b1000 E
b1000 H
b1000 L
bz "
bz /
bz 0
bz 5
bz 6
bz ;
bz <
bz A
bz I
bz `
1K
1J
0=
0b
0a
b1100000000 .
b1100000000 R
b1100000000 S
b1100000000 T
0!
#90
b11 '
b11 N
b11 _
b110000000000000000000 $
b110000000000000000000 Q
b110000000000000000000 f
b10 d
b10 +
b10 O
b10 P
b10 [
b10 e
b1000 (
b1000 D
b1000 F
1!
#95
0-
0M
b1000 "
b1000 /
b1000 0
b1000 5
b1000 6
b1000 ;
b1000 <
b1000 A
b1000 I
b1000 `
0K
0J
17
1C
b110000000000000000000 .
b110000000000000000000 R
b110000000000000000000 S
b110000000000000000000 T
0!
#100
b100 '
b100 N
b100 _
b10000000000000000000000 $
b10000000000000000000000 Q
b10000000000000000000000 f
b11 +
b11 O
b11 P
b11 [
b11 e
b1000 *
b1000 9
b1000 Y
b1000 :
1!
#105
bz "
bz /
bz 0
bz 5
bz 6
bz ;
bz <
bz A
bz I
bz `
1^
07
0C
b10000000000000000000000 .
b10000000000000000000000 R
b10000000000000000000000 S
b10000000000000000000000 T
0!
#110
b1001000000000000000000 $
b1001000000000000000000 Q
b1001000000000000000000 f
b100 +
b100 O
b100 P
b100 [
b100 e
1!
#115
b101 '
b101 N
b101 _
b1000 "
b1000 /
b1000 0
b1000 5
b1000 6
b1000 ;
b1000 <
b1000 A
b1000 I
b1000 `
0^
18
1=
b1001000000000000000000 .
b1001000000000000000000 R
b1001000000000000000000 S
b1001000000000000000000 T
0!
#120
b110 '
b110 N
b110 _
b1100000000 $
b1100000000 Q
b1100000000 f
b101 +
b101 O
b101 P
b101 [
b101 e
b1000 )
b1000 ?
b1000 G
b1000 @
1!
#125
1-
1M
b1010101 %
b1010101 E
b1010101 H
b1010101 L
bz "
bz /
bz 0
bz 5
bz 6
bz ;
bz <
bz A
bz I
bz `
1K
1J
08
0=
b1100000000 .
b1100000000 R
b1100000000 S
b1100000000 T
0!
#130
b111 '
b111 N
b111 _
b100010000000010000000000 $
b100010000000010000000000 Q
b100010000000010000000000 f
b110 +
b110 O
b110 P
b110 [
b110 e
b1010101 (
b1010101 D
b1010101 F
1!
#135
b0 '
b0 N
b0 _
0-
0M
b1010101 "
b1010101 /
b1010101 0
b1010101 5
b1010101 6
b1010101 ;
b1010101 <
b1010101 A
b1010101 I
b1010101 `
11
1]
0K
0J
1C
b100010000000010000000000 .
b100010000000010000000000 R
b100010000000010000000000 S
b100010000000010000000000 T
0!
#140
b1000000000011000000 $
b1000000000011000000 Q
b1000000000011000000 f
b0 +
b0 O
b0 P
b0 [
b0 e
b1010101 ,
b1010101 3
b1010101 4
1!
#145
b1 '
b1 N
b1 _
b10 "
b10 /
b10 0
b10 5
b10 6
b10 ;
b10 <
b10 A
b10 I
b10 `
01
0]
0C
1=
1b
1a
b1000000000011000000 .
b1000000000011000000 R
b1000000000011000000 S
b1000000000011000000 T
0!
#150
b10 '
b10 N
b10 _
b1100000000 $
b1100000000 Q
b1100000000 f
b11 c
b1 +
b1 O
b1 P
b1 [
b1 e
b10 )
b10 ?
b10 G
b10 @
1!
#155
1-
1M
b10101 %
b10101 E
b10101 H
b10101 L
bz "
bz /
bz 0
bz 5
bz 6
bz ;
bz <
bz A
bz I
bz `
1K
1J
0=
0b
0a
b1100000000 .
b1100000000 R
b1100000000 S
b1100000000 T
0!
#160
b11 '
b11 N
b11 _
b110000000000000000000 $
b110000000000000000000 Q
b110000000000000000000 f
b10 +
b10 O
b10 P
b10 [
b10 e
b11 d
b10101 (
b10101 D
b10101 F
1!
#165
0-
0M
b10101 "
b10101 /
b10101 0
b10101 5
b10101 6
b10101 ;
b10101 <
b10101 A
b10101 I
b10101 `
0K
0J
17
1C
b110000000000000000000 .
b110000000000000000000 R
b110000000000000000000 S
b110000000000000000000 T
0!
#170
b100 '
b100 N
b100 _
b10000000000000000000000 $
b10000000000000000000000 Q
b10000000000000000000000 f
b11 +
b11 O
b11 P
b11 [
b11 e
b1000 &
b1000 Z
b1000 \
b10101 *
b10101 9
b10101 Y
b10101 :
1!
#175
b1000 '
b1000 N
b1000 _
bz "
bz /
bz 0
bz 5
bz 6
bz ;
bz <
bz A
bz I
bz `
1^
07
0C
b10000000000000000000000 .
b10000000000000000000000 R
b10000000000000000000000 S
b10000000000000000000000 T
0!
#180
b1001000000000000000000 $
b1001000000000000000000 Q
b1001000000000000000000 f
b1000 +
b1000 O
b1000 P
b1000 [
b1000 e
1!
#185
b1001 '
b1001 N
b1001 _
b10101 "
b10101 /
b10101 0
b10101 5
b10101 6
b10101 ;
b10101 <
b10101 A
b10101 I
b10101 `
0^
18
1=
b1001000000000000000000 .
b1001000000000000000000 R
b1001000000000000000000 S
b1001000000000000000000 T
0!
#190
b1010 '
b1010 N
b1010 _
b100000000 $
b100000000 Q
b100000000 f
b1001 +
b1001 O
b1001 P
b1001 [
b1001 e
b10101 )
b10101 ?
b10101 G
b10101 @
1!
#195
1-
1M
bz "
bz /
bz 0
bz 5
bz 6
bz ;
bz <
bz A
bz I
bz `
1J
08
0=
b100000000 .
b100000000 R
b100000000 S
b100000000 T
0!
#200
b1011 '
b1011 N
b1011 _
b100000000100000000000000 $
b100000000100000000000000 Q
b100000000100000000000000 f
b1010 +
b1010 O
b1010 P
b1010 [
b1010 e
1!
#205
b1010101 "
b1010101 /
b1010101 0
b1010101 5
b1010101 6
b1010101 ;
b1010101 <
b1010101 A
b1010101 I
b1010101 `
b0 '
b0 N
b0 _
0-
0M
12
1]
0J
b100000000100000000000000 .
b100000000100000000000000 R
b100000000100000000000000 S
b100000000100000000000000 T
0!
#210
b1000000000011000000 $
b1000000000011000000 Q
b1000000000011000000 f
b0 +
b0 O
b0 P
b0 [
b0 e
1!
#215
b1 '
b1 N
b1 _
b11 "
b11 /
b11 0
b11 5
b11 6
b11 ;
b11 <
b11 A
b11 I
b11 `
02
0]
1=
1b
1a
b1000000000011000000 .
b1000000000011000000 R
b1000000000011000000 S
b1000000000011000000 T
0!
#220
b10 '
b10 N
b10 _
b1100000000 $
b1100000000 Q
b1100000000 f
b1 +
b1 O
b1 P
b1 [
b1 e
b100 c
b11 )
b11 ?
b11 G
b11 @
1!
#225
1-
1M
b1010 %
b1010 E
b1010 H
b1010 L
bz "
bz /
bz 0
bz 5
bz 6
bz ;
bz <
bz A
bz I
bz `
1K
1J
0=
0b
0a
b1100000000 .
b1100000000 R
b1100000000 S
b1100000000 T
0!
#230
b11 '
b11 N
b11 _
b110000000000000000000 $
b110000000000000000000 Q
b110000000000000000000 f
b100 d
b10 +
b10 O
b10 P
b10 [
b10 e
b1010 (
b1010 D
b1010 F
1!
#235
0-
0M
b1010 "
b1010 /
b1010 0
b1010 5
b1010 6
b1010 ;
b1010 <
b1010 A
b1010 I
b1010 `
0K
0J
17
1C
b110000000000000000000 .
b110000000000000000000 R
b110000000000000000000 S
b110000000000000000000 T
0!
#240
b100 '
b100 N
b100 _
b10000000000000000000000 $
b10000000000000000000000 Q
b10000000000000000000000 f
b11 +
b11 O
b11 P
b11 [
b11 e
b100 &
b100 Z
b100 \
b1010 *
b1010 9
b1010 Y
b1010 :
1!
#245
bz "
bz /
bz 0
bz 5
bz 6
bz ;
bz <
bz A
bz I
bz `
1^
07
0C
b10000000000000000000000 .
b10000000000000000000000 R
b10000000000000000000000 S
b10000000000000000000000 T
0!
#250
b1001000000000000000000 $
b1001000000000000000000 Q
b1001000000000000000000 f
b100 +
b100 O
b100 P
b100 [
b100 e
1!
#255
b101 '
b101 N
b101 _
b1010 "
b1010 /
b1010 0
b1010 5
b1010 6
b1010 ;
b1010 <
b1010 A
b1010 I
b1010 `
0^
18
1=
b1001000000000000000000 .
b1001000000000000000000 R
b1001000000000000000000 S
b1001000000000000000000 T
0!
#260
b110 '
b110 N
b110 _
b1100000000 $
b1100000000 Q
b1100000000 f
b101 +
b101 O
b101 P
b101 [
b101 e
b1010 )
b1010 ?
b1010 G
b1010 @
1!
#265
1-
1M
b101 %
b101 E
b101 H
b101 L
bz "
bz /
bz 0
bz 5
bz 6
bz ;
bz <
bz A
bz I
bz `
1K
1J
08
0=
b1100000000 .
b1100000000 R
b1100000000 S
b1100000000 T
0!
#270
b111 '
b111 N
b111 _
b100010000000010000000000 $
b100010000000010000000000 Q
b100010000000010000000000 f
b110 +
b110 O
b110 P
b110 [
b110 e
b101 (
b101 D
b101 F
1!
#275
b0 '
b0 N
b0 _
0-
0M
b101 "
b101 /
b101 0
b101 5
b101 6
b101 ;
b101 <
b101 A
b101 I
b101 `
11
1]
0K
0J
1C
b100010000000010000000000 .
b100010000000010000000000 R
b100010000000010000000000 S
b100010000000010000000000 T
0!
#280
b1000000000011000000 $
b1000000000011000000 Q
b1000000000011000000 f
b0 +
b0 O
b0 P
b0 [
b0 e
b101 ,
b101 3
b101 4
1!
#285
b1 '
b1 N
b1 _
b100 "
b100 /
b100 0
b100 5
b100 6
b100 ;
b100 <
b100 A
b100 I
b100 `
01
0]
0C
1=
1b
1a
b1000000000011000000 .
b1000000000011000000 R
b1000000000011000000 S
b1000000000011000000 T
0!
#290
b10 '
b10 N
b10 _
b1100000000 $
b1100000000 Q
b1100000000 f
b101 c
b1 +
b1 O
b1 P
b1 [
b1 e
b100 )
b100 ?
b100 G
b100 @
1!
#295
1-
1M
bz "
bz /
bz 0
bz 5
bz 6
bz ;
bz <
bz A
bz I
bz `
1K
1J
0=
0b
0a
b1100000000 .
b1100000000 R
b1100000000 S
b1100000000 T
0!
#300
b11 '
b11 N
b11 _
b110000000000000000000 $
b110000000000000000000 Q
b110000000000000000000 f
b10 +
b10 O
b10 P
b10 [
b10 e
b101 d
1!
#305
0-
0M
b101 "
b101 /
b101 0
b101 5
b101 6
b101 ;
b101 <
b101 A
b101 I
b101 `
0K
0J
17
1C
b110000000000000000000 .
b110000000000000000000 R
b110000000000000000000 S
b110000000000000000000 T
0!
#310
b100 '
b100 N
b100 _
b10000000000000000000000 $
b10000000000000000000000 Q
b10000000000000000000000 f
b11 +
b11 O
b11 P
b11 [
b11 e
b101 *
b101 9
b101 Y
b101 :
1!
#315
bz "
bz /
bz 0
bz 5
bz 6
bz ;
bz <
bz A
bz I
bz `
1^
07
0C
b10000000000000000000000 .
b10000000000000000000000 R
b10000000000000000000000 S
b10000000000000000000000 T
0!
#320
b1001000000000000000000 $
b1001000000000000000000 Q
b1001000000000000000000 f
b100 +
b100 O
b100 P
b100 [
b100 e
1!
#325
b101 '
b101 N
b101 _
b101 "
b101 /
b101 0
b101 5
b101 6
b101 ;
b101 <
b101 A
b101 I
b101 `
0^
18
1=
b1001000000000000000000 .
b1001000000000000000000 R
b1001000000000000000000 S
b1001000000000000000000 T
0!
#330
b110 '
b110 N
b110 _
b1100000000 $
b1100000000 Q
b1100000000 f
b101 +
b101 O
b101 P
b101 [
b101 e
b101 )
b101 ?
b101 G
b101 @
1!
#335
1-
1M
bz %
bz E
bz H
bz L
bz "
bz /
bz 0
bz 5
bz 6
bz ;
bz <
bz A
bz I
bz `
1K
1J
08
0=
b1100000000 .
b1100000000 R
b1100000000 S
b1100000000 T
0!
#340
b111 '
b111 N
b111 _
b100010000000010000000000 $
b100010000000010000000000 Q
b100010000000010000000000 f
b110 +
b110 O
b110 P
b110 [
b110 e
bz (
bz D
bz F
1!
#345
b0 '
b0 N
b0 _
0-
0M
11
1]
0K
0J
1C
b100010000000010000000000 .
b100010000000010000000000 R
b100010000000010000000000 S
b100010000000010000000000 T
0!
#350
b1000000000011000000 $
b1000000000011000000 Q
b1000000000011000000 f
b0 +
b0 O
b0 P
b0 [
b0 e
bz ,
bz 3
bz 4
1!
#355
b1 '
b1 N
b1 _
b101 "
b101 /
b101 0
b101 5
b101 6
b101 ;
b101 <
b101 A
b101 I
b101 `
01
0]
0C
1=
1b
1a
b1000000000011000000 .
b1000000000011000000 R
b1000000000011000000 S
b1000000000011000000 T
0!
#360
b10 '
b10 N
b10 _
b1100000000 $
b1100000000 Q
b1100000000 f
b1 +
b1 O
b1 P
b1 [
b1 e
b110 c
1!
#365
1-
1M
bz "
bz /
bz 0
bz 5
bz 6
bz ;
bz <
bz A
bz I
bz `
1K
1J
0=
0b
0a
b1100000000 .
b1100000000 R
b1100000000 S
b1100000000 T
0!
#370
b11 '
b11 N
b11 _
b110000000000000000000 $
b110000000000000000000 Q
b110000000000000000000 f
b110 d
b10 +
b10 O
b10 P
b10 [
b10 e
1!
#375
0-
0M
0K
0J
17
1C
b110000000000000000000 .
b110000000000000000000 R
b110000000000000000000 S
b110000000000000000000 T
0!
#380
b100 '
b100 N
b100 _
b10000000000000000000000 $
b10000000000000000000000 Q
b10000000000000000000000 f
b11 +
b11 O
b11 P
b11 [
b11 e
bx &
bx Z
bx \
bz *
bz 9
bz Y
bz :
1!
#385
bx '
bx N
bx _
1^
07
0C
b10000000000000000000000 .
b10000000000000000000000 R
b10000000000000000000000 S
b10000000000000000000000 T
0!
#390
bx $
bx Q
bx f
bx +
bx O
bx P
bx [
bx e
1!
#395
1-
1M
bx "
bx /
bx 0
bx 5
bx 6
bx ;
bx <
bx A
bx I
bx `
x2
x1
x^
x]
xK
xJ
x8
x7
xC
x=
xb
xa
bx .
bx R
bx S
bx T
0!
